mongo_aggro/__init__.py
mongo_aggro/accumulators.py
mongo_aggro/base.py
mongo_aggro/operators.py
mongo_aggro/stages.py
mongo_aggro-0.1.0.dist-info/METADATA
mongo_aggro-0.1.0.dist-info/WHEEL
mongo_aggro-0.1.0.dist-info/licenses/LICENSE
mongo_aggro-0.1.0.dist-info/RECORD
