Metadata-Version: 2.4
Name: mongo-aggro
Version: 0.1.0
Summary: MongoDB Aggregation Pipeline Builder with Pydantic
License-Expression: MIT
License-File: LICENSE
Keywords: mongodb,aggregation,pipeline,pydantic,database
Author: Hamed Ghenaat
Requires-Python: >=3.12
Classifier: Development Status :: 4 - Beta
Classifier: Intended Audience :: Developers
Classifier: License :: OSI Approved :: MIT License
Classifier: Operating System :: OS Independent
Classifier: Programming Language :: Python :: 3
Classifier: Programming Language :: Python :: 3.12
Classifier: Topic :: Database
Classifier: Topic :: Software Development :: Libraries :: Python Modules
Classifier: Typing :: Typed
Provides-Extra: dev
Provides-Extra: docs
Provides-Extra: test
Requires-Dist: black (>=24.10.0) ; extra == "dev"
Requires-Dist: isort (>=5.13.2) ; extra == "dev"
Requires-Dist: mkdocs (>=1.6.0) ; extra == "docs"
Requires-Dist: mkdocs-material (>=9.5.0) ; extra == "docs"
Requires-Dist: mkdocstrings (>=0.27.0) ; extra == "docs"
Requires-Dist: mkdocstrings-python (>=1.12.0) ; extra == "docs"
Requires-Dist: mypy (>=1.13.0) ; extra == "dev"
Requires-Dist: pre-commit (>=4.0.0) ; extra == "dev"
Requires-Dist: pydantic (>=2.10.0)
Requires-Dist: pytest (>=8.0.0) ; extra == "test"
Requires-Dist: pytest-cov (>=6.0.0) ; extra == "test"
Requires-Dist: pytest-mock (>=3.14.0) ; extra == "test"
Requires-Dist: pyupgrade (>=3.19.0) ; extra == "dev"
Requires-Dist: ruff (>=0.8.0) ; extra == "dev"
Project-URL: Documentation, https://hamedghenaat.github.io/mongo-aggro/
Project-URL: Homepage, https://github.com/hamedghenaat/mongo-aggro
Project-URL: Repository, https://github.com/hamedghenaat/mongo-aggro
